Metadata-Version: 2.1
Name: rope
Version: 1.13.0
Summary: a python refactoring library...
Author-email: Ali Gholami Rudi <aligrudi@users.sourceforge.net>
Maintainer-email: Lie Ryan <lieryan.24@proton.me>
License: LGPL-3.0-or-later
Project-URL: Source, https://github.com/python-rope/rope
Project-URL: Documentation, https://rope.readthedocs.io/
Classifier: Development Status :: 4 - Beta
Classifier: Operating System :: OS Independent
Classifier: Environment :: X11 Applications
Classifier: Environment :: Win32 (MS Windows)
Classifier: Environment :: MacOS X
Classifier: Intended Audience :: Developers
Classifier: License :: OSI Approved :: GNU Lesser General Public License v3 or later (LGPLv3+)
Classifier: Natural Language :: English
Classifier: Programming Language :: Python
Classifier: Programming Language :: Python :: 3
Classifier: Programming Language :: Python :: 3.8
Classifier: Programming Language :: Python :: 3.9
Classifier: Programming Language :: Python :: 3.10
Classifier: Programming Language :: Python :: 3.11
Classifier: Programming Language :: Python :: 3.12
Classifier: Topic :: Software Development
Requires-Python: >=3.8
License-File: COPYING
Requires-Dist: pytoolconfig[global]>=1.2.2
Provides-Extra: doc
Requires-Dist: pytoolconfig[doc]; extra == "doc"
Requires-Dist: sphinx>=4.5.0; extra == "doc"
Requires-Dist: sphinx-autodoc-typehints>=1.18.1; extra == "doc"
Requires-Dist: sphinx-rtd-theme>=1.0.0; extra == "doc"
Provides-Extra: dev
Requires-Dist: pytest>=7.0.1; extra == "dev"
Requires-Dist: pytest-cov>=4.1.0; extra == "dev"
Requires-Dist: pytest-timeout>=2.1.0; extra == "dev"
Requires-Dist: build>=0.7.0; extra == "dev"
Requires-Dist: pre-commit>=2.20.0; extra == "dev"
Provides-Extra: release
Requires-Dist: toml>=0.10.2; extra == "release"
Requires-Dist: twine>=4.0.2; extra == "release"
Requires-Dist: pip-tools>=6.12.1; extra == "release"
